pandastock/__init__.py
pandastock/candles/__init__.py
pandastock/candles/accessor.py
pandastock/candles/data.py
pandastock/candles/types.py
pandastock/indicators/__init__.py
pandastock/indicators/base.py
pandastock/indicators/lsma.py
pandastock/indicators/macd.py
pandastock/indicators/rsi.py
pandastock/indicators/sma.py
pandastock/indicators/stoch_rsi.py
pandastock/trades/__init__.py
pandastock/trades/accessor.py
pandastock/trades/data.py
pandastock/trades/types.py
pandastock-0.0.3.3.dist-info/licenses/LICENSE
pandastock-0.0.3.3.dist-info/METADATA
pandastock-0.0.3.3.dist-info/WHEEL
pandastock-0.0.3.3.dist-info/top_level.txt
pandastock-0.0.3.3.dist-info/RECORD
