Metadata-Version: 2.4
Name: pandastock
Version: 0.0.3.3
Summary: Pandas extension for financial data processing and visualization
Author-email: Alexey Sheshukov <alexeyshesh@yandex.ru>
License: MIT
Project-URL: Homepage, https://github.com/alexeyshesh/pandastock
Project-URL: Repository, https://github.com/alexeyshesh/pandastock
Requires-Python: >=3.11
License-File: LICENSE
Requires-Dist: pandas
Requires-Dist: matplotlib
Dynamic: license-file
